rdf4j_python/__init__.py
rdf4j_python/_client/__init__.py
rdf4j_python/_client/_client.py
rdf4j_python/_driver/__init__.py
rdf4j_python/_driver/_async_named_graph.py
rdf4j_python/_driver/_async_rdf4j_db.py
rdf4j_python/_driver/_async_repository.py
rdf4j_python/exception/__init__.py
rdf4j_python/exception/repo_exception.py
rdf4j_python/model/__init__.py
rdf4j_python/model/_namespace.py
rdf4j_python/model/_repository_info.py
rdf4j_python/model/repository_config.py
rdf4j_python/model/term.py
rdf4j_python/model/vocabulary.py
rdf4j_python/utils/__init__.py
rdf4j_python/utils/const.py
rdf4j_python/utils/helpers.py
rdf4j_python-0.1.6.dist-info/licenses/LICENSE
rdf4j_python-0.1.6.dist-info/METADATA
rdf4j_python-0.1.6.dist-info/WHEEL
rdf4j_python-0.1.6.dist-info/top_level.txt
rdf4j_python-0.1.6.dist-info/RECORD
