Metadata-Version: 2.4
Name: rdf4j-python
Version: 0.1.6
Summary: The Python client for RDF4J
Author-email: Chengxu Bian <cbian564@gmail.com>
Requires-Python: >=3.10
License-File: LICENSE
Requires-Dist: httpx>=0.28.1
Requires-Dist: pyoxigraph>=0.4.10
Provides-Extra: sparqlwrapper
Requires-Dist: sparqlwrapper>=2.0.0; extra == "sparqlwrapper"
Dynamic: license-file
